{
  "formatVersion": 1,
  "database": {
    "version": 7,
    "identityHash": "c9ce2aa3d49b2efa95f65208e3cb3bff",
    "entities": [
      {
        "tableName": "products",
        "createSql": "CREATE TABLE IF NOT EXISTS `${TABLE_NAME}` (`id` INTEGER PRIMARY KEY AUTOINCREMENT NOT NULL, `name` TEXT NOT NULL, `price` REAL NOT NULL, `imageUrl` TEXT NOT NULL, `quantity` INTEGER NOT NULL)",
        "fields": [
          {
            "fieldPath": "id",
            "columnName": "id",
            "affinity": "INTEGER",
            "notNull": true
          },
          {
            "fieldPath": "name",
            "columnName": "name",
            "affinity": "TEXT",
            "notNull": true
          },
          {
            "fieldPath": "price",
            "columnName": "price",
            "affinity": "REAL",
            "notNull": true
          },
          {
            "fieldPath": "imageUrl",
            "columnName": "imageUrl",
            "affinity": "TEXT",
            "notNull": true
          },
          {
            "fieldPath": "quantity",
            "columnName": "quantity",
            "affinity": "INTEGER",
            "notNull": true
          }
        ],
        "primaryKey": {
          "autoGenerate": true,
          "columnNames": [
            "id"
          ]
        },
        "indices": [],
        "foreignKeys": []
      },
      {
        "tableName": "cart_items",
        "createSql": "CREATE TABLE IF NOT EXISTS `${TABLE_NAME}` (`id` INTEGER PRIMARY KEY AUTOINCREMENT NOT NULL, `product_id` INTEGER NOT NULL, `product_name` TEXT NOT NULL, `quantity` INTEGER NOT NULL, `price` REAL NOT NULL)",
        "fields": [
          {
            "fieldPath": "id",
            "columnName": "id",
            "affinity": "INTEGER",
            "notNull": true
          },
          {
            "fieldPath": "productId",
            "columnName": "product_id",
            "affinity": "INTEGER",
            "notNull": true
          },
          {
            "fieldPath": "productName",
            "columnName": "product_name",
            "affinity": "TEXT",
            "notNull": true
          },
          {
            "fieldPath": "quantity",
            "columnName": "quantity",
            "affinity": "INTEGER",
            "notNull": true
          },
          {
            "fieldPath": "price",
            "columnName": "price",
            "affinity": "REAL",
            "notNull": true
          }
        ],
        "primaryKey": {
          "autoGenerate": true,
          "columnNames": [
            "id"
          ]
        },
        "indices": [],
        "foreignKeys": []
      }
    ],
    "views": [],
    "setupQueries": [
      "CREATE TABLE IF NOT EXISTS room_master_table (id INTEGER PRIMARY KEY,identity_hash TEXT)",
      "INSERT OR REPLACE INTO room_master_table (id,identity_hash) VALUES(42, 'c9ce2aa3d49b2efa95f65208e3cb3bff')"
    ]
  }
}